setup.py
src/urltest/__init__.py
src/urltest.egg-info/PKG-INFO
src/urltest.egg-info/SOURCES.txt
src/urltest.egg-info/dependency_links.txt
src/urltest.egg-info/requires.txt
src/urltest.egg-info/top_level.txt
src/urltest/tests/__init__.py
src/urltest/tests/common.py
src/urltest/tests/generators.py
src/urltest/tests/runner.py
src/urltest/tests/utilities.py